pkvpm/__init__.py
pkvpm/parser.py
tests/__init__.py
tests/test_parser.py
pkvpm-1.0.3.dist-info/LICENSE
pkvpm-1.0.3.dist-info/METADATA
pkvpm-1.0.3.dist-info/WHEEL
pkvpm-1.0.3.dist-info/top_level.txt
pkvpm-1.0.3.dist-info/RECORD
