Metadata-Version: 2.1
Name: pkvpm
Version: 1.0.3
Summary: A package for Polymorphic Key-Value Path Mapping (PKVPM)
Home-page: https://github.com/PKVPM/PKVPM
Author: PKVPM Organization
Author-email: PKVPM@PKVPM.ORG
Classifier: License :: OSI Approved :: MIT License
Classifier: Programming Language :: Python :: 3
Classifier: Intended Audience :: Developers
Classifier: Topic :: Software Development :: Libraries :: Python Modules
License-File: LICENSE
Requires-Dist: PyYAML
